lbg_tools/__init__.py
lbg_tools/_igm_inoue.py
lbg_tools/_igm_madau.py
lbg_tools/_version.py
lbg_tools/bandpass.py
lbg_tools/completeness.py
lbg_tools/cosmo_utils.py
lbg_tools/igm.py
lbg_tools/library.py
lbg_tools/luminosity_function.py
lbg_tools/py.typed
lbg_tools/sed.py
lbg_tools/tomography.py
lbg_tools/data/bandpasses/bandpass_g_v1p9.dat
lbg_tools/data/bandpasses/bandpass_i_v1p9.dat
lbg_tools/data/bandpasses/bandpass_r_v1p9.dat
lbg_tools/data/bandpasses/bandpass_u_v1p9.dat
lbg_tools/data/bandpasses/bandpass_y_v1p9.dat
lbg_tools/data/bandpasses/bandpass_z_v1p9.dat
lbg_tools/data/completeness/completeness_g.dat
lbg_tools/data/completeness/completeness_i.dat
lbg_tools/data/completeness/completeness_r.dat
lbg_tools/data/completeness/completeness_u.dat
lbg_tools/data/completeness/completeness_z.dat
lbg_tools-1.6.0.dist-info/licenses/LICENSE
lbg_tools-1.6.0.dist-info/METADATA
lbg_tools-1.6.0.dist-info/WHEEL
lbg_tools-1.6.0.dist-info/top_level.txt
lbg_tools-1.6.0.dist-info/RECORD
