Metadata-Version: 2.4
Name: lbg_tools
Version: 1.6.0
Author-email: John Franklin Crenshaw <jfcrenshaw@gmail.com>
License: MIT License
Project-URL: Source Code, https://github.com/jfcrenshaw/lbg_tools
Classifier: Development Status :: 4 - Beta
Classifier: License :: OSI Approved :: MIT License
Classifier: Intended Audience :: Developers
Classifier: Intended Audience :: Science/Research
Classifier: Operating System :: OS Independent
Classifier: Programming Language :: Python
Requires-Python: >=3.11
License-File: LICENSE
Requires-Dist: astropy
Requires-Dist: numpy
Requires-Dist: pandas
Requires-Dist: scipy
Provides-Extra: dev
Requires-Dist: black; extra == "dev"
Requires-Dist: flake8; extra == "dev"
Requires-Dist: isort; extra == "dev"
Requires-Dist: jupyter; extra == "dev"
Requires-Dist: jupyterlab; extra == "dev"
Requires-Dist: matplotlib; extra == "dev"
Requires-Dist: mypy; extra == "dev"
Requires-Dist: pre-commit; extra == "dev"
Requires-Dist: pytest; extra == "dev"
Requires-Dist: pytest-cov; extra == "dev"
Dynamic: license-file
